<?xml version="1.0" standalone="yes"?>
<Program>
<LetCommand>
<SequentialDeclaration>
<SequentialDeclaration>
<SequentialDeclaration>
<VarDeclaration>
<Identifier value="i"/>
<SimpleTypeDenoter>
<Identifier value="Char"/>
</SimpleTypeDenoter>
</VarDeclaration>
<VarDeclaration>
<Identifier value="j"/>
<SimpleTypeDenoter>
<Identifier value="Integer"/>
</SimpleTypeDenoter>
</VarDeclaration>
</SequentialDeclaration>
<ConstDeclaration>
<Identifier value="k"/>
<IntegerExpression>
<IntegerLiteral value="8"/>
</IntegerExpression>
</ConstDeclaration>
</SequentialDeclaration>
<TypeDeclaration>
<Identifier value="dia"/>
<SimpleTypeDenoter>
<Identifier value="Integer"/>
</SimpleTypeDenoter>
</TypeDeclaration>
</SequentialDeclaration>
<SequentialCommand>
<CallCommand>
<Identifier value="put"/>
<SingleActualParameterSequence>
<ConstActualParameter>
<VnameExpression>
<SimpleVname>
<Identifier value="i"/>
</SimpleVname>
</VnameExpression>
</ConstActualParameter>
</SingleActualParameterSequence>
</CallCommand>
<CallCommand>
<Identifier value="put"/>
<SingleActualParameterSequence>
<ConstActualParameter>
<VnameExpression>
<SimpleVname>
<Identifier value="i"/>
</SimpleVname>
</VnameExpression>
</ConstActualParameter>
</SingleActualParameterSequence>
</CallCommand>
</SequentialCommand>
</LetCommand>
</Program>
